gnenv/__init__.py
gnenv/environ.py
gnenv-0.1.2.dist-info/LICENSE.txt
gnenv-0.1.2.dist-info/METADATA
gnenv-0.1.2.dist-info/WHEEL
gnenv-0.1.2.dist-info/top_level.txt
gnenv-0.1.2.dist-info/RECORD
