Metadata-Version: 2.1
Name: gnenv
Version: 0.1.2
Summary: UNKNOWN
Home-page: UNKNOWN
Author: Oscar Eriksson
Author-email: oscar.eriks@gmail.com
License: LICENSE.txt
Keywords: environment
Platform: UNKNOWN
Requires-Dist: strict-rfc3339 (==0.7)
